wsgiproxy/__init__.py
wsgiproxy/proxies.py
wsgiproxy/requests_client.py
wsgiproxy/test_wsgiproxy.py
wsgiproxy/urllib3_client.py
WSGIProxy2-0.5.1.dist-info/COPYING
WSGIProxy2-0.5.1.dist-info/METADATA
WSGIProxy2-0.5.1.dist-info/WHEEL
WSGIProxy2-0.5.1.dist-info/entry_points.txt
WSGIProxy2-0.5.1.dist-info/top_level.txt
WSGIProxy2-0.5.1.dist-info/RECORD
