Metadata-Version: 1.1
Name: WSGIProxy2
Version: 0.5.1
Summary: A WSGI Proxy with various http client backends
Home-page: https://github.com/gawel/WSGIProxy2/
Author: Gael Pasgrimaud
Author-email: gael@gawel.org
License: MIT
Keywords: wsgi proxy
Platform: UNKNOWN
Classifier: License :: OSI Approved :: MIT License
Classifier: Topic :: Internet :: WWW/HTTP :: WSGI :: Application
Classifier: Programming Language :: Python :: 3.7
Classifier: Programming Language :: Python :: 3.8
Classifier: Programming Language :: Python :: 3.9
